MANIFEST.in
README.md
setup.py
TOPSIS_Sezalpreet_101803216/topsis.py
TOPSIS_Sezalpreet_101803216.egg-info/PKG-INFO
TOPSIS_Sezalpreet_101803216.egg-info/SOURCES.txt
TOPSIS_Sezalpreet_101803216.egg-info/dependency_links.txt
TOPSIS_Sezalpreet_101803216.egg-info/requires.txt
TOPSIS_Sezalpreet_101803216.egg-info/top_level.txt