Metadata-Version: 2.1
Name: TOPSIS-Sezalpreet-101803216
Version: 0.2
Summary: This is python program for implementation of topsis
Home-page: https://github.com/sezalprkaur/Topsis.git
Author: Sezalpreet Kaur
Author-email: sezalprkaur@gmail.com
License: MIT
Platform: UNKNOWN
Classifier: Development Status :: 3 - Alpha
Classifier: Intended Audience :: Developers
Classifier: Topic :: Software Development :: Build Tools
Classifier: License :: OSI Approved :: MIT License
Classifier: Programming Language :: Python :: 3
Classifier: Programming Language :: Python :: 3.4
Classifier: Programming Language :: Python :: 3.5
Classifier: Programming Language :: Python :: 3.6
Classifier: Programming Language :: Python :: 3.7
Classifier: Programming Language :: Python :: 3.8
